[{"make": "Lexus", "model": "CT200h", "car_model": "2017 Lexus CT200h Base Model", "review_title": "Very luxurious hatchback", "reviewer_info": "Posted by SHAYAAN AHMAD on Oct 17, 2020", "familiarity": "Familiarity: I owned this car.", "review_text": "The car is very stylish and it is very sporty looking hatchback with a very luxurious interior. The car is filled with feautures but it is very expensive. The car is stable at 200km and it can go over 200 no problem. This car can compete with audi a3 civic hatchback and Corolla hatch back but the lexus is better than all of them", "style": "5 rating", "comfort_rating": "5 rating", "fuel_economy": "4 rating", "perfomance": "4 rating", "value_for_money": "2 rating", "overall_rating": 4, "helpful_votes": "(0 out of 0 people found this review helpful)"}, {"make": "Lexus", "model": "CT200h", "car_model": "2017 Lexus CT200h Base Model", "review_title": "Great buy and excellent value for money", "reviewer_info": "Posted by SHAYAAN AHMAD on Oct 03, 2020", "familiarity": "Familiarity: I owned this car.", "review_text": "Very sporty exterior with drl, leds and a a lot of style but very low to the ground \nThe interior is like an aircraft because it has a lot of buttons in the center console \nThe main features of this hatchback are\nDual temp climate control\nMultimedia bluetooth steering wheel \n3 driving modes eco, normal, sport\n6 cd changer \n7 inch screen with apple car play\nHill holder \n8 airbags", "style": "5 rating", "comfort_rating": "5 rating", "fuel_economy": "5 rating", "perfomance": "4 rating", "value_for_money": "2 rating", "overall_rating": 4, "helpful_votes": "(0 out of 0 people found this review helpful)"}]