[{"make": "Porsche", "model": "Boxster", "car_model": "Porsche Boxster 997 ||", "review_title": "Some what good", "reviewer_info": "Posted by tauheedz on Sep 18, 2012", "familiarity": "", "review_text": "comfortable and great performance. i like this car because of its style. usually good for racing but inside city you cannot get the full performance. its good car if you do road journeys. I recommend this car to every one who can afford to pay for it.", "style": "5 rating", "comfort_rating": "5 rating", "fuel_economy": "5 rating", "perfomance": "3 rating", "value_for_money": "2 rating", "overall_rating": 4, "helpful_votes": "(2 out of 3 people found this review helpful)"}, {"make": "Porsche", "model": "Boxster", "car_model": "Porsche Boxster S 3.2", "review_title": "Nice One", "reviewer_info": "Posted by Sakura2011 on Jun 28, 2011", "familiarity": "", "review_text": "ITS A VERY VERY VERY NICE AND COMFORTABLE CAR.BUT TOO MUCH EXPENSIVE.I HAVE THIS ONE AND ALWAYS USE MY CAR FOR DATE ONLY.OTHERWISE I USE MY COROLA  GLI. ITS A GREAT CAR.IF ANYONE WANT TO BUY IT FOR REGULAR USE PLZ DONT DO THAT.IT CAN ONLY AND ONLY BE USED FOR DATE AS I SAID EARLIER.", "style": "3 rating", "comfort_rating": "4 rating", "fuel_economy": "5 rating", "perfomance": "2 rating", "value_for_money": "5 rating", "overall_rating": 5, "helpful_votes": "(0 out of 7 people found this review helpful)"}]